setup.cfg
setup.py
dm/__init__.py
dm.zope.reseller.egg-info/PKG-INFO
dm.zope.reseller.egg-info/SOURCES.txt
dm.zope.reseller.egg-info/dependency_links.txt
dm.zope.reseller.egg-info/namespace_packages.txt
dm.zope.reseller.egg-info/not-zip-safe
dm.zope.reseller.egg-info/requires.txt
dm.zope.reseller.egg-info/top_level.txt
dm/zope/__init__.py
dm/zope/reseller/LICENSE.txt
dm/zope/reseller/README.txt
dm/zope/reseller/VERSION.txt
dm/zope/reseller/__init__.py
dm/zope/reseller/article.py
dm/zope/reseller/client.py
dm/zope/reseller/config.py
dm/zope/reseller/configure.zcml
dm/zope/reseller/delivery.py
dm/zope/reseller/i18n.py
dm/zope/reseller/interfaces.py
dm/zope/reseller/lib.py
dm/zope/reseller/order.py
dm/zope/reseller/permission.zcml
dm/zope/reseller/provider.py
dm/zope/reseller/stock.py
dm/zope/reseller/translations.zcml
dm/zope/reseller/update.py
dm/zope/reseller/browser/__init__.py
dm/zope/reseller/browser/admin.py
dm/zope/reseller/browser/article.py
dm/zope/reseller/browser/browsermenu.py
dm/zope/reseller/browser/client.py
dm/zope/reseller/browser/configure.zcml
dm/zope/reseller/browser/controlled_page.pt
dm/zope/reseller/browser/crud-row.pt
dm/zope/reseller/browser/crud-table.pt
dm/zope/reseller/browser/delivery.py
dm/zope/reseller/browser/interfaces.py
dm/zope/reseller/browser/list.pt
dm/zope/reseller/browser/menu.py
dm/zope/reseller/browser/menu_bar.pt
dm/zope/reseller/browser/order.py
dm/zope/reseller/browser/provider.py
dm/zope/reseller/browser/root.py
dm/zope/reseller/browser/standard_macros.pt
dm/zope/reseller/browser/stock.py
dm/zope/reseller/browser/subforms.pt
dm/zope/reseller/browser/traversal.py
dm/zope/reseller/browser/view.py
dm/zope/reseller/browser/wrappedform.pt
dm/zope/reseller/browser/resource/assign.png
dm/zope/reseller/browser/resource/delete.png
dm/zope/reseller/browser/resource/edit.png
dm/zope/reseller/browser/resource/error.png
dm/zope/reseller/browser/resource/green.png
dm/zope/reseller/browser/resource/jquery-1.11.0.min.js
dm/zope/reseller/browser/resource/link.png
dm/zope/reseller/browser/resource/ok.png
dm/zope/reseller/browser/resource/reactivate.png
dm/zope/reseller/browser/resource/red.png
dm/zope/reseller/browser/resource/reopen.png
dm/zope/reseller/browser/resource/reseller.css
