Metadata-Version: 1.1
Name: dm.zope.reseller
Version: 1.0.3
Summary: Zope package for reselling
Home-page: http://pypi.python.org/pypi/dm.zope.reseller
Author: Dieter Maurer
Author-email: dieter@handshake.de
License: BSD
Keywords: product order delivery management reselling
Platform: UNKNOWN
Classifier: Development Status :: 5 - Production/Stable
Classifier: Intended Audience :: Developers
Classifier: Environment :: Web Environment
Classifier: Intended Audience :: End Users/Desktop
Classifier: License :: OSI Approved :: BSD License
Classifier: Framework :: Zope2
Classifier: Operating System :: OS Independent
Classifier: Programming Language :: Python
Classifier: Topic :: Home Automation
Classifier: Topic :: Internet :: WWW/HTTP :: Dynamic Content
Classifier: Topic :: Office/Business
